Metadata-Version: 1.1
Name: mnft
Version: 0.1.0
Summary: Model NFT Pytorch Lightning Callback
Home-page: https://github.com/SharifElfouly/NFT-Pytorch-Callback
Author: Sharif Elfouly
Author-email: selfouly@gmail.com
License: BSD 2-clause
Platform: UNKNOWN
Classifier: Programming Language :: Python :: 3
Classifier: Programming Language :: Python :: 3.4
Classifier: Programming Language :: Python :: 3.5
